platzi/__init__.py
platzi/async_api.py
platzi/cli.py
platzi/collectors.py
platzi/constants.py
platzi/helpers.py
platzi/logger.py
platzi/m3u8.py
platzi/models.py
platzi/utils.py
platzi_downloader-0.4.3.dist-info/LICENCE
platzi_downloader-0.4.3.dist-info/METADATA
platzi_downloader-0.4.3.dist-info/WHEEL
platzi_downloader-0.4.3.dist-info/entry_points.txt
platzi_downloader-0.4.3.dist-info/RECORD
