Metadata-Version: 2.3
Name: platzi-downloader
Version: 0.4.3
Summary: Download your courses from platzi
License: MIT
Keywords: Platzi,downloader,courses
Author: iamyare
Author-email: iamyare@no-reply.com
Requires-Python: >=3.10,<4.0
Classifier: License :: OSI Approved :: MIT License
Classifier: Operating System :: OS Independent
Classifier: Programming Language :: Python :: 3
Classifier: Programming Language :: Python :: 3.10
Classifier: Programming Language :: Python :: 3.11
Classifier: Programming Language :: Python :: 3.12
Classifier: Programming Language :: Python :: 3.13
Requires-Dist: aiofiles (>=24.1.0,<25.0.0)
Requires-Dist: beautifulsoup4 (>=4.13.3,<5.0.0)
Requires-Dist: html2markdown (>=0.1.7,<0.2.0)
Requires-Dist: humps (>=0.2.2,<0.3.0)
Requires-Dist: platformdirs (>=4.3.6,<5.0.0)
Requires-Dist: pydantic (>=2.9.2,<3.0.0)
Requires-Dist: pyhumps (>=3.8.0,<4.0.0)
Requires-Dist: pytest-playwright (>=0.5.2,<0.6.0)
Requires-Dist: rnet (>=2.2.1,<3.0.0)
Requires-Dist: tqdm (>=4.67.0,<5.0.0)
Requires-Dist: typer (>=0.13.0,<0.14.0)
Requires-Dist: unidecode (>=1.3.8,<2.0.0)
